canacb/__init__.py
canacb/cfg.py
canacb/info.py
canacb/main.py
canacb/nameserver.py
canacb/pfo.py
canacb/tools.py
canacb/ui.py
canacb/views.py
canacb/widgets.py
canacb/images/tinycopy.png
canacb/images/tinyleaf.png
canacb-0.4.dist-info/entry_points.txt
canacb-0.4.dist-info/licenses/LICENSE
canacb-0.4.dist-info/WHEEL
canacb-0.4.dist-info/METADATA
canacb-0.4.dist-info/RECORD
