Metadata-Version: 2.4
Name: canacb
Version: 0.4
Summary: canacb - Adjusted cost base tracker for Canadian investors
Keywords: adjusted cost base,acb,canada,canadian,capital,gains,tax
Author-email: Norbert Schlenker <canacb@libra-investments.com>
Requires-Python: >=3.5
License-Expression: MIT
Classifier: Development Status :: 4 - Beta
Classifier: Intended Audience :: End Users/Desktop
Classifier: Programming Language :: Python :: 3
Classifier: Topic :: Office/Business :: Financial :: Investment
License-File: LICENSE
Requires-Dist: black ; extra == "dev"
Requires-Dist: flake8 ; extra == "dev"
Requires-Dist: flit ; extra == "dev"
Requires-Dist: pylint ; extra == "dev"
Project-URL: Bug Tracker, https://not-a-url.org
Project-URL: Changelog, https://not-a-url.org
Project-URL: Documentation, https://not-a-url.org
Project-URL: Download, https://not-a-url.org
Project-URL: Homepage, https://github.com/NorbertSchlenker/canacb
Provides-Extra: dev
